llmware/__init__.py
llmware/agents.py
llmware/configs.py
llmware/embeddings.py
llmware/gguf_configs.py
llmware/library.py
llmware/model_configs.py
llmware/models.py
llmware/parsers.py
llmware/prompts.py
llmware/resources.py
llmware/retrieval.py
llmware/setup.py
llmware/util.py
llmware/web_services.py
llmware/lib/darwin/arm64/llmware/libgraph_llmware.so
llmware/lib/darwin/arm64/llmware/liboffice_llmware.so
llmware/lib/darwin/arm64/llmware/libpdf_llmware.so
llmware/lib/darwin/arm64/llmware/.dylibs/libbson-1.0.0.0.0.dylib
llmware/lib/darwin/arm64/llmware/.dylibs/liblzma.5.dylib
llmware/lib/darwin/arm64/llmware/.dylibs/libmongoc-1.0.0.0.0.dylib
llmware/lib/darwin/arm64/llmware/.dylibs/libpng16.16.dylib
llmware/lib/darwin/arm64/llmware/.dylibs/libpq.5.dylib
llmware/lib/darwin/arm64/llmware/.dylibs/libsnappy.1.1.10.dylib
llmware/lib/darwin/arm64/llmware/.dylibs/libsqlite3.0.dylib
llmware/lib/darwin/arm64/llmware/.dylibs/libxml2.2.dylib
llmware/lib/darwin/arm64/llmware/.dylibs/libzip.5.5.dylib
llmware/lib/darwin/arm64/llmware/.dylibs/libzstd.1.5.5.dylib
llmware/lib/gguf/gguf_arm64/ggml-base.dll
llmware/lib/gguf/gguf_arm64/ggml-cpu.dll
llmware/lib/gguf/gguf_arm64/ggml.dll
llmware/lib/gguf/gguf_arm64/libllama.dll
llmware/lib/gguf/gguf_linux_cuda/libggml-base.so
llmware/lib/gguf/gguf_linux_cuda/libggml-cpu.so
llmware/lib/gguf/gguf_linux_cuda/libggml-cuda.so
llmware/lib/gguf/gguf_linux_cuda/libggml.so
llmware/lib/gguf/gguf_linux_cuda/libllama.so
llmware/lib/gguf/gguf_linux_x86/libggml-base.so
llmware/lib/gguf/gguf_linux_x86/libggml-cpu.so
llmware/lib/gguf/gguf_linux_x86/libggml.so
llmware/lib/gguf/gguf_linux_x86/libllama.so
llmware/lib/gguf/gguf_mac/libggml-base.dylib
llmware/lib/gguf/gguf_mac/libggml-blas.dylib
llmware/lib/gguf/gguf_mac/libggml-cpu.dylib
llmware/lib/gguf/gguf_mac/libggml-metal.dylib
llmware/lib/gguf/gguf_mac/libggml.dylib
llmware/lib/gguf/gguf_mac/libllama.dylib
llmware/lib/gguf/gguf_win_cuda/ggml-base.dll
llmware/lib/gguf/gguf_win_cuda/ggml-base.lib
llmware-0.4.3.dist-info/licenses/LICENSE
llmware-0.4.3.dist-info/licenses/NOTICE
llmware-0.4.3.dist-info/METADATA
llmware-0.4.3.dist-info/WHEEL
llmware-0.4.3.dist-info/top_level.txt
llmware-0.4.3.dist-info/zip-safe
llmware-0.4.3.dist-info/RECORD
