Metadata-Version: 2.4
Name: llmware
Version: 0.4.3
Summary: An enterprise-grade LLM-based development framework, tools, and fine-tuned models
Home-page: https://github.com/llmware-ai
Author: llmware
Author-email: support@aibloks.com
Project-URL: Repository, https://github.com/llmware-ai/llmware
Keywords: ai,llm,rag,data,development
Classifier: Development Status :: 4 - Beta
Classifier: Intended Audience :: Developers
Classifier: Topic :: Software Development
Classifier: License :: OSI Approved :: Apache Software License
Classifier: Programming Language :: Python :: 3.9
Classifier: Programming Language :: Python :: 3.10
Classifier: Programming Language :: Python :: 3.11
Classifier: Programming Language :: Python :: 3.12
Classifier: Programming Language :: Python :: 3.13
Requires-Python: >=3.9
License-File: LICENSE
License-File: NOTICE
Requires-Dist: huggingface-hub>=0.19.4
Requires-Dist: numpy>=1.23.2
Requires-Dist: requests>=2.32.0
Requires-Dist: tokenizers>=0.15.0
Requires-Dist: boto3>=1.24.53
Requires-Dist: colorama==0.4.6
Provides-Extra: milvus
Requires-Dist: pymilvus<=2.5.1; extra == "milvus"
Provides-Extra: chromadb
Requires-Dist: chromadb>=0.4.22; extra == "chromadb"
Provides-Extra: pinecone
Requires-Dist: pinecone-client==3.0.0; extra == "pinecone"
Provides-Extra: lancedb
Requires-Dist: lancedb==0.5.0; extra == "lancedb"
Provides-Extra: qdrant
Requires-Dist: qdrant-client==1.7.0; extra == "qdrant"
Provides-Extra: whisper
Requires-Dist: soundfile>=0.12.0; extra == "whisper"
Requires-Dist: soxr>=0.5.0; extra == "whisper"
Provides-Extra: postgres
Requires-Dist: psycopg-binary==3.1.17; extra == "postgres"
Requires-Dist: psycopg==3.1.17; extra == "postgres"
Requires-Dist: pgvector==0.2.4; extra == "postgres"
Provides-Extra: redis
Requires-Dist: redis==5.0.1; extra == "redis"
Provides-Extra: mongo
Requires-Dist: pymongo>=4.7.0; extra == "mongo"
Provides-Extra: neo4j
Requires-Dist: neo4j==5.16.0; extra == "neo4j"
Provides-Extra: full
Requires-Dist: pymongo>=4.7.0; extra == "full"
Requires-Dist: torch>=1.13.1; extra == "full"
Requires-Dist: transformers>=4.36.0; extra == "full"
Requires-Dist: einops>=0.7.0; extra == "full"
Requires-Dist: Wikipedia-API>=0.6.0; extra == "full"
Requires-Dist: openai>=1.0; extra == "full"
Requires-Dist: datasets>=2.15.0; extra == "full"
Requires-Dist: yfinance>=0.2.38; extra == "full"
Requires-Dist: pymilvus<=2.5.1; extra == "full"
Requires-Dist: chromadb>=0.4.22; extra == "full"
Requires-Dist: streamlit; extra == "full"
Requires-Dist: Flask; extra == "full"
Requires-Dist: psycopg-binary==3.1.17; extra == "full"
Requires-Dist: psycopg==3.1.17; extra == "full"
Requires-Dist: pgvector==0.2.4; extra == "full"
Requires-Dist: soundfile>=0.12.0; extra == "full"
Requires-Dist: soxr>=0.5.0; extra == "full"
Dynamic: author
Dynamic: author-email
Dynamic: classifier
Dynamic: description
Dynamic: description-content-type
Dynamic: home-page
Dynamic: keywords
Dynamic: license-file
Dynamic: project-url
Dynamic: provides-extra
Dynamic: requires-dist
Dynamic: requires-python
Dynamic: summary
